{
  "hash": "b8e265d4",
  "configHash": "d306262e",
  "lockfileHash": "136e72e4",
  "browserHash": "0a57f9b0",
  "optimized": {
    "vue": {
      "src": "../../../../node_modules/vue/dist/vue.runtime.esm-bundler.js",
      "file": "vue.js",
      "fileHash": "bb92402f",
      "needsInterop": false
    },
    "vitepress > @vue/devtools-api": {
      "src": "../../../../node_modules/vitepress/node_modules/@vue/devtools-api/dist/index.js",
      "file": "vitepress___@vue_devtools-api.js",
      "fileHash": "e9cdcd13",
      "needsInterop": false
    },
    "vitepress > @vueuse/core": {
      "src": "../../../../node_modules/@vueuse/core/index.mjs",
      "file": "vitepress___@vueuse_core.js",
      "fileHash": "9f277e98",
      "needsInterop": false
    },
    "@theme/index": {
      "src": "../../../../node_modules/vitepress/dist/client/theme-default/index.js",
      "file": "@theme_index.js",
      "fileHash": "053ce7c1",
      "needsInterop": false
    }
  },
  "chunks": {
    "chunk-4I4JYJZN": {
      "file": "chunk-4I4JYJZN.js"
    },
    "chunk-CKQ4TNQ3": {
      "file": "chunk-CKQ4TNQ3.js"
    }
  }
}